{
  "urls": [
      {
          "id": 1,
          "long_url": "https://images.unsplash.com/photo-1531898418865-480b7090470f?ixlib=rb-1.2.1&ixid=eyJhcHBfaWQiOjEyMDd9&auto=format&fit=crop&w=934&q=80",
          "short_url": "http://localhost:3001/useshorturl/1",
          "title": "Awesome photo"
      },
      {
          "long_url": "https://tab.gladly.io/newtab/auth/?mandatory=true&app=tab",
          "title": "Test",
          "id": 2,
          "short_url": "http://localhost:3001/useshorturl/2"
      },
      {
          "long_url": "https://stackoverflow.com/questions/47970276/is-using-async-componentdidmount-good",
          "title": "Test 2",
          "id": 3,
          "short_url": "http://localhost:3001/useshorturl/3"
      }
  ]
}